{
  "culture": "sl",
  "texts": {
    "Feature:IdentityGroup": "Identiteta",
    "Feature:TwoFactor": "Obnašanje dveh dejavnikov",
    "Feature:TwoFactorDescription": "Nastavite vedenje dveh faktorjev. Izbirne vrednosti: Izbirno, Onemogočeno, Prisilno",
    "Feature:TwoFactor.Optional": "Neobvezno",
    "Feature:TwoFactor.Disabled": "Onemogočeno",
    "Feature:TwoFactor.Forced": "Prisilno",
    "Feature:EnableLdapLogin": "Omogoči prijavo v Ldap",
    "Feature:EnableLdapLoginDescription": "Omogoči prijavo v Ldap",
    "Feature:EnableOAuthLogin": "Omogoči prijavo v OAuth",
    "Feature:EnableOAuthLoginDescription": "Omogoči prijavo v OAuth",
    "DisplayName:Abp.Identity.TwoFactorBehaviour": "Obnašanje dveh faktorjev",
    "Description:Abp.Identity.TwoFactorBehaviour": "Obnašanje dveh faktorjev",
    "DisplayName:Abp.Identity.UsersCanChange": "Dovoli uporabnikom, da spremenijo dva faktorja.",
    "Description:Abp.Identity.UsersCanChange": "Dovoli uporabnikom, da spremenijo dva faktorja.",
    "DisplayName:Abp.Identity.EnableLdapLogin": "Omogoči prijavo v Ldap",
    "Description:Abp.Identity.EnableLdapLogin": "Omogoči prijavo v Ldap",
    "DisplayName:Abp.Identity.EnableOAuthLogin": "Omogoči prijavo v OAuth",
    "Description:Abp.Identity.EnableOAuthLogin": "Omogoči prijavo v OAuth",
    "DisplayName:Abp.Identity.Authority": "Oblast",
    "Description:Abp.Identity.Authority": "Oblast",
    "DisplayName:Abp.Identity.ClientId": "ID odjemalca",
    "Description:Abp.Identity.ClientId": "ID odjemalca",
    "DisplayName:Abp.Identity.ClientSecret": "Skrivnost stranke",
    "Description:Abp.Identity.ClientSecret": "Skrivnost stranke",
    "DisplayName:Abp.Identity.Scope": "Obseg",
    "Description:Abp.Identity.Scope": "Obseg",
    "DisplayName:Abp.Identity.RequireHttpsMetadata": "Zahtevajte metapodatke https",
    "Description:Abp.Identity.RequireHttpsMetadata": "Zahtevajte metapodatke https",
    "Feature:MaximumUserCount": "Največje število uporabnikov",
    "Feature:MaximumUserCountDescription": "0 = neomejeno",
    "Volo.Abp.Identity:010009": "Doseženo največje dovoljeno število uporabnikov! Ta najemnik ima dovoljeno največ {MaxUserCount} uporabnikov.",
    "LdapPasswordPlaceholder": "Vnesite za posodobitev gesla",
    "LdapLoginSettings": "Nastavitve za prijavo v Ldap",
    "OAuthLoginSettings": "Nastavitve za prijavo v OAuth",
    "Menu:Identity:Ldap": "Račun Ldap",
    "IdentitySettingsLdap": "Ldap",
    "IdentitySettingsOAuth": "OAuth",
    "IdentitySettingsGeneral": "General"
  }
}
